{
  "formatVersion": 1,
  "database": {
    "version": 2,
    "identityHash": "31f3283ce63a350fd8789155af6a4425",
    "entities": [
      {
        "tableName": "users",
        "createSql": "CREATE TABLE IF NOT EXISTS `${TABLE_NAME}` (`id` INTEGER PRIMARY KEY AUTOINCREMENT, `name` TEXT NOT NULL, `lastname` TEXT NOT NULL, `username` TEXT NOT NULL, `password` TEXT NOT NULL)",
        "fields": [
          {
            "fieldPath": "id",
            "columnName": "id",
            "affinity": "INTEGER"
          },
          {
            "fieldPath": "name",
            "columnName": "name",
            "affinity": "TEXT",
            "notNull": true
          },
          {
            "fieldPath": "lastname",
            "columnName": "lastname",
            "affinity": "TEXT",
            "notNull": true
          },
          {
            "fieldPath": "username",
            "columnName": "username",
            "affinity": "TEXT",
            "notNull": true
          },
          {
            "fieldPath": "password",
            "columnName": "password",
            "affinity": "TEXT",
            "notNull": true
          }
        ],
        "primaryKey": {
          "autoGenerate": true,
          "columnNames": [
            "id"
          ]
        }
      },
      {
        "tableName": "categories",
        "createSql": "CREATE TABLE IF NOT EXISTS `${TABLE_NAME}` (`id` INTEGER PRIMARY KEY AUTOINCREMENT, `name` TEXT NOT NULL, `items` INTEGER NOT NULL, `userId` INTEGER NOT NULL, FOREIGN KEY(`userId`) REFERENCES `users`(`id`) ON UPDATE NO ACTION ON DELETE CASCADE )",
        "fields": [
          {
            "fieldPath": "id",
            "columnName": "id",
            "affinity": "INTEGER"
          },
          {
            "fieldPath": "name",
            "columnName": "name",
            "affinity": "TEXT",
            "notNull": true
          },
          {
            "fieldPath": "items",
            "columnName": "items",
            "affinity": "INTEGER",
            "notNull": true
          },
          {
            "fieldPath": "userId",
            "columnName": "userId",
            "affinity": "INTEGER",
            "notNull": true
          }
        ],
        "primaryKey": {
          "autoGenerate": true,
          "columnNames": [
            "id"
          ]
        },
        "indices": [
          {
            "name": "index_categories_userId",
            "unique": false,
            "columnNames": [
              "userId"
            ],
            "orders": [],
            "createSql": "CREATE INDEX IF NOT EXISTS `index_categories_userId` ON `${TABLE_NAME}` (`userId`)"
          }
        ],
        "foreignKeys": [
          {
            "table": "users",
            "onDelete": "CASCADE",
            "onUpdate": "NO ACTION",
            "columns": [
              "userId"
            ],
            "referencedColumns": [
              "id"
            ]
          }
        ]
      },
      {
        "tableName": "items",
        "createSql": "CREATE TABLE IF NOT EXISTS `${TABLE_NAME}` (`id` INTEGER PRIMARY KEY AUTOINCREMENT, `categoryId` INTEGER NOT NULL, `name` TEXT NOT NULL, `date` INTEGER NOT NULL, `price` REAL NOT NULL, FOREIGN KEY(`categoryId`) REFERENCES `categories`(`id`) ON UPDATE NO ACTION ON DELETE CASCADE )",
        "fields": [
          {
            "fieldPath": "id",
            "columnName": "id",
            "affinity": "INTEGER"
          },
          {
            "fieldPath": "categoryId",
            "columnName": "categoryId",
            "affinity": "INTEGER",
            "notNull": true
          },
          {
            "fieldPath": "name",
            "columnName": "name",
            "affinity": "TEXT",
            "notNull": true
          },
          {
            "fieldPath": "date",
            "columnName": "date",
            "affinity": "INTEGER",
            "notNull": true
          },
          {
            "fieldPath": "price",
            "columnName": "price",
            "affinity": "REAL",
            "notNull": true
          }
        ],
        "primaryKey": {
          "autoGenerate": true,
          "columnNames": [
            "id"
          ]
        },
        "indices": [
          {
            "name": "index_items_categoryId",
            "unique": false,
            "columnNames": [
              "categoryId"
            ],
            "orders": [],
            "createSql": "CREATE INDEX IF NOT EXISTS `index_items_categoryId` ON `${TABLE_NAME}` (`categoryId`)"
          }
        ],
        "foreignKeys": [
          {
            "table": "categories",
            "onDelete": "CASCADE",
            "onUpdate": "NO ACTION",
            "columns": [
              "categoryId"
            ],
            "referencedColumns": [
              "id"
            ]
          }
        ]
      }
    ],
    "setupQueries": [
      "CREATE TABLE IF NOT EXISTS room_master_table (id INTEGER PRIMARY KEY,identity_hash TEXT)",
      "INSERT OR REPLACE INTO room_master_table (id,identity_hash) VALUES(42, '31f3283ce63a350fd8789155af6a4425')"
    ]
  }
}